src/__init__.py
src/black_scholes.py
src/instrument_manager.py
src/option_chain_app.py
src/stock_mappings.py
src/token_manager.py
theoprice-0.1.1.dist-info/licenses/LICENSE
theoprice-0.1.1.dist-info/METADATA
theoprice-0.1.1.dist-info/WHEEL
theoprice-0.1.1.dist-info/entry_points.txt
theoprice-0.1.1.dist-info/top_level.txt
theoprice-0.1.1.dist-info/RECORD
