Metadata-Version: 2.4
Name: theoprice
Version: 0.1.1
Summary: A Python CLI application for fetching real-time options trading data from Upstox API with Black-Scholes Greeks calculations
Home-page: https://github.com/yourusername/theoprice
Author: princecodes
Author-email: princecodes <princecodes@duck.com>
License: MIT
Project-URL: Homepage, https://github.com/yourusername/theoprice
Project-URL: Documentation, https://github.com/yourusername/theoprice#readme
Project-URL: Repository, https://github.com/yourusername/theoprice
Project-URL: Issues, https://github.com/yourusername/theoprice/issues
Keywords: upstox,options,trading,black-scholes,greeks,indian-markets,cli
Classifier: Development Status :: 4 - Beta
Classifier: Intended Audience :: Financial and Insurance Industry
Classifier: Topic :: Office/Business :: Financial :: Investment
Classifier: Programming Language :: Python :: 3
Classifier: Programming Language :: Python :: 3.8
Classifier: Programming Language :: Python :: 3.9
Classifier: Programming Language :: Python :: 3.10
Classifier: Programming Language :: Python :: 3.11
Classifier: Programming Language :: Python :: 3.12
Classifier: Operating System :: OS Independent
Classifier: Environment :: Console
Requires-Python: >=3.8
License-File: LICENSE
Requires-Dist: upstox-python-sdk==2.17.0
Requires-Dist: rich>=13.7.0
Requires-Dist: inquirer>=3.2.4
Requires-Dist: python-dotenv>=1.0.0
Requires-Dist: scipy>=1.11.4
Requires-Dist: requests
Dynamic: author
Dynamic: home-page
Dynamic: license-file
Dynamic: requires-python
